[{"_path":"/features/authentication","title":"Authentication"},{"_path":"/features/authorization","title":"Authorization"},{"_path":"/features/business","title":"Business"},{"_path":"/features/caching","title":"Caching"},{"_path":"/features/coding-style","title":"Coding Style"},{"_path":"/features/communication","title":"Communication"},{"_path":"/features/core","title":"Core"},{"_path":"/features/database","title":"Database"},{"_path":"/features/exception-handling","title":"Exception Handling"},{"_path":"/features/greeting","title":"Greeting"},{"_path":"/features/lifetime","title":"Lifetime"},{"_path":"/features/logging","title":"Logging"},{"_path":"/features/mock-overrider","title":"Mock Overrider"},{"_path":"/features/orm","title":"ORM"}]