{"_path":"/features/database","_dir":"features","_draft":false,"_partial":false,"_locale":"","_empty":false,"title":"Database","description":"This feature provides a database setup to be used both in development and\nproduction setups.","body":{"type":"root","children":[{"type":"element","tag":"h1","props":{"id":"database"},"children":[{"type":"text","value":"Database"}]},{"type":"element","tag":"p","props":{},"children":[{"type":"text","value":"This feature provides a database setup to be used both in development and\nproduction setups."}]},{"type":"element","tag":"p","props":{},"children":[{"type":"text","value":"Add this feature using "},{"type":"element","tag":"code-inline","props":{},"children":[{"type":"text","value":"AddDatabase()"}]},{"type":"text","value":" extension;"}]},{"type":"element","tag":"code","props":{"code":"app.Features.AddDatabase(...);\n","language":"csharp","meta":null},"children":[{"type":"element","tag":"pre","props":{},"children":[{"type":"element","tag":"code","props":{"__ignoreMap":""},"children":[{"type":"element","tag":"span","props":{"class":"line","line":1},"children":[{"type":"element","tag":"span","props":{"class":"ct-cd40c1"},"children":[{"type":"text","value":"app"}]},{"type":"element","tag":"span","props":{"class":"ct-7d8c81"},"children":[{"type":"text","value":"."}]},{"type":"element","tag":"span","props":{"class":"ct-cd40c1"},"children":[{"type":"text","value":"Features"}]},{"type":"element","tag":"span","props":{"class":"ct-7d8c81"},"children":[{"type":"text","value":"."}]},{"type":"element","tag":"span","props":{"class":"ct-b833e6"},"children":[{"type":"text","value":"AddDatabase"}]},{"type":"element","tag":"span","props":{"class":"ct-7d8c81"},"children":[{"type":"text","value":"(...);"}]}]}]}]}]},{"type":"element","tag":"h2","props":{"id":"inmemory"},"children":[{"type":"text","value":"InMemory"}]},{"type":"element","tag":"p","props":{},"children":[{"type":"text","value":"Adds in-memory database setup."}]},{"type":"element","tag":"code","props":{"code":"c => c.InMemory()\n","language":"csharp","meta":null},"children":[{"type":"element","tag":"pre","props":{},"children":[{"type":"element","tag":"code","props":{"__ignoreMap":""},"children":[{"type":"element","tag":"span","props":{"class":"line","line":1},"children":[{"type":"element","tag":"span","props":{"class":"ct-cd40c1"},"children":[{"type":"text","value":"c"}]},{"type":"element","tag":"span","props":{"class":"ct-7d8c81"},"children":[{"type":"text","value":" => "}]},{"type":"element","tag":"span","props":{"class":"ct-cd40c1"},"children":[{"type":"text","value":"c"}]},{"type":"element","tag":"span","props":{"class":"ct-7d8c81"},"children":[{"type":"text","value":"."}]},{"type":"element","tag":"span","props":{"class":"ct-b833e6"},"children":[{"type":"text","value":"InMemory"}]},{"type":"element","tag":"span","props":{"class":"ct-7d8c81"},"children":[{"type":"text","value":"()"}]}]}]}]}]},{"type":"element","tag":"h2","props":{"id":"sqlite"},"children":[{"type":"text","value":"Sqlite"}]},{"type":"element","tag":"p","props":{},"children":[{"type":"text","value":"Adds local Sqlite database setup which creates local sqlite database in\ndocuments folder with given name."}]},{"type":"element","tag":"code","props":{"code":"c => c.AddSqlite(fileName = \"test.db\")\n","language":"csharp","meta":null},"children":[{"type":"element","tag":"pre","props":{},"children":[{"type":"element","tag":"code","props":{"__ignoreMap":""},"children":[{"type":"element","tag":"span","props":{"class":"line","line":1},"children":[{"type":"element","tag":"span","props":{"class":"ct-cd40c1"},"children":[{"type":"text","value":"c"}]},{"type":"element","tag":"span","props":{"class":"ct-7d8c81"},"children":[{"type":"text","value":" => "}]},{"type":"element","tag":"span","props":{"class":"ct-cd40c1"},"children":[{"type":"text","value":"c"}]},{"type":"element","tag":"span","props":{"class":"ct-7d8c81"},"children":[{"type":"text","value":"."}]},{"type":"element","tag":"span","props":{"class":"ct-b833e6"},"children":[{"type":"text","value":"AddSqlite"}]},{"type":"element","tag":"span","props":{"class":"ct-7d8c81"},"children":[{"type":"text","value":"("}]},{"type":"element","tag":"span","props":{"class":"ct-cd40c1"},"children":[{"type":"text","value":"fileName"}]},{"type":"element","tag":"span","props":{"class":"ct-7d8c81"},"children":[{"type":"text","value":" = "}]},{"type":"element","tag":"span","props":{"class":"ct-1ff04b"},"children":[{"type":"text","value":"\"test.db\""}]},{"type":"element","tag":"span","props":{"class":"ct-7d8c81"},"children":[{"type":"text","value":")"}]}]}]}]}]},{"type":"element","tag":"h2","props":{"id":"mysql"},"children":[{"type":"text","value":"MySql"}]},{"type":"element","tag":"p","props":{},"children":[{"type":"text","value":"Adds MySql database setup which gets connection parameters from "},{"type":"element","tag":"code-inline","props":{},"children":[{"type":"text","value":"app.settings"}]},{"type":"text","value":"."}]},{"type":"element","tag":"code","props":{"code":"c => c.MySql()\n","language":"csharp","meta":null},"children":[{"type":"element","tag":"pre","props":{},"children":[{"type":"element","tag":"code","props":{"__ignoreMap":""},"children":[{"type":"element","tag":"span","props":{"class":"line","line":1},"children":[{"type":"element","tag":"span","props":{"class":"ct-cd40c1"},"children":[{"type":"text","value":"c"}]},{"type":"element","tag":"span","props":{"class":"ct-7d8c81"},"children":[{"type":"text","value":" => "}]},{"type":"element","tag":"span","props":{"class":"ct-cd40c1"},"children":[{"type":"text","value":"c"}]},{"type":"element","tag":"span","props":{"class":"ct-7d8c81"},"children":[{"type":"text","value":"."}]},{"type":"element","tag":"span","props":{"class":"ct-b833e6"},"children":[{"type":"text","value":"MySql"}]},{"type":"element","tag":"span","props":{"class":"ct-7d8c81"},"children":[{"type":"text","value":"()"}]}]}]}]}]},{"type":"element","tag":"style","children":[{"type":"text","value":".ct-1ff04b{color:#CE9178}\n.ct-b833e6{color:#DCDCAA}\n.ct-7d8c81{color:#D4D4D4}\n.ct-cd40c1{color:#9CDCFE}"}]}],"toc":{"title":"","searchDepth":2,"depth":2,"links":[{"id":"inmemory","depth":2,"text":"InMemory"},{"id":"sqlite","depth":2,"text":"Sqlite"},{"id":"mysql","depth":2,"text":"MySql"}]}},"_type":"markdown","_id":"content:features:database.md","_source":"content","_file":"features/database.md","_extension":"md"}